lofn/__init__.py
lofn/api.py
lofn/docker_handler.py
lofn/hdfs_handler.py
lofn/tmp_file_handler.py
lofn/base/__init__.py
lofn/base/hdfs.py
lofn/base/tmp.py
lofn-0.4.0.dist-info/DESCRIPTION.rst
lofn-0.4.0.dist-info/METADATA
lofn-0.4.0.dist-info/RECORD
lofn-0.4.0.dist-info/WHEEL
lofn-0.4.0.dist-info/metadata.json
lofn-0.4.0.dist-info/top_level.txt
