Metadata-Version: 2.0
Name: lofn
Version: 0.4.0
Summary: Lightweight Orchestration For Now: Wrapper for serial tools using Spark and Docker to parallelize
Home-page: https://github.com/michaeltneylon/lofn
Author: Michael T. Neylon
Author-email: neylon_michael_t@lilly.com
License: Apache License 2.0
Download-URL: https://github.com/michaeltneylon/lofn/archive/0.4.0.tar.gz
Platform: UNKNOWN
Classifier: License :: OSI Approved :: Apache Software License
Classifier: Programming Language :: Python
Classifier: Programming Language :: Python :: 2
Classifier: Programming Language :: Python :: 3
Classifier: Topic :: System :: Distributed Computing
